odoo10_addon_medical_center-10.0.1.0.0.99.dev10-py2.7-nspkg.pth
odoo/addons/medical_center/README.rst
odoo/addons/medical_center/__init__.py
odoo/addons/medical_center/__manifest__.py
odoo/addons/medical_center/demo/medical_center.xml
odoo/addons/medical_center/i18n/es.po
odoo/addons/medical_center/i18n/es_AR.po
odoo/addons/medical_center/i18n/es_CO.po
odoo/addons/medical_center/i18n/fr.po
odoo/addons/medical_center/i18n/nl_NL.po
odoo/addons/medical_center/i18n/pt_BR.po
odoo/addons/medical_center/i18n/ro.po
odoo/addons/medical_center/models/__init__.py
odoo/addons/medical_center/models/medical_center.py
odoo/addons/medical_center/models/medical_patient.py
odoo/addons/medical_center/models/res_partner.py
odoo/addons/medical_center/security/ir.model.access.csv
odoo/addons/medical_center/static/description/icon.png
odoo/addons/medical_center/static/src/img/medical-center-avatar-full.png
odoo/addons/medical_center/static/src/img/medical-center-avatar.png
odoo/addons/medical_center/tests/__init__.py
odoo/addons/medical_center/tests/test_medical_center.py
odoo/addons/medical_center/views/medical_center.xml
odoo/addons/medical_center/views/medical_menu.xml
odoo/addons/medical_center/views/medical_patient.xml
odoo10_addon_medical_center-10.0.1.0.0.99.dev10.dist-info/DESCRIPTION.rst
odoo10_addon_medical_center-10.0.1.0.0.99.dev10.dist-info/METADATA
odoo10_addon_medical_center-10.0.1.0.0.99.dev10.dist-info/RECORD
odoo10_addon_medical_center-10.0.1.0.0.99.dev10.dist-info/WHEEL
odoo10_addon_medical_center-10.0.1.0.0.99.dev10.dist-info/metadata.json
odoo10_addon_medical_center-10.0.1.0.0.99.dev10.dist-info/namespace_packages.txt
odoo10_addon_medical_center-10.0.1.0.0.99.dev10.dist-info/top_level.txt
