Metadata-Version: 2.0
Name: odoo10-addon-medical-center
Version: 10.0.1.0.0.99.dev10
Summary: Adds a concept of Medical Centers to Patients.
Home-page: https://laslabs.com
Author: LasLabs, Odoo Community Association (OCA)
Author-email: support@odoo-community.org
License: GPL-3
Platform: UNKNOWN
Classifier: Programming Language :: Python
Classifier: Framework :: Odoo
Classifier: License :: OSI Approved :: GNU General Public License v3 (GPLv3)
Requires-Python: ~=2.7
Requires-Dist: odoo (<10.1dev,>=10.0)
Requires-Dist: odoo10-addon-medical
